setup.py
django_transaction_signals/__init__.py
django_transaction_signals.egg-info/PKG-INFO
django_transaction_signals.egg-info/SOURCES.txt
django_transaction_signals.egg-info/dependency_links.txt
django_transaction_signals.egg-info/top_level.txt