Metadata-Version: 1.0
Name: django-transaction-signals
Version: 1.0.0
Summary: django-transaction-signals adds post_commit and post_rollback signal handlers to Django
Home-page: https://github.com/davehughes/django-transaction-signals
Author: David Hughes
Author-email: d@vidhughes.com
License: UNKNOWN
Platform: UNKNOWN
